web3_wizzard_lib/__init__.py
web3_wizzard_lib/launcher.py
web3_wizzard_lib/main.py
web3_wizzard_lib/core/__init__.py
web3_wizzard_lib/core/contract/__init__.py
web3_wizzard_lib/core/contract/aavecontract.py
web3_wizzard_lib/core/contract/alienswap_contract.py
web3_wizzard_lib/core/contract/arena_games_contract.py
web3_wizzard_lib/core/contract/basiliskcontract.py
web3_wizzard_lib/core/contract/bilinear_contract.py
web3_wizzard_lib/core/contract/bungee.py
web3_wizzard_lib/core/contract/cog_erc20.py
web3_wizzard_lib/core/contract/compound_v3.py
web3_wizzard_lib/core/contract/compund_v3_bulker.py
web3_wizzard_lib/core/contract/coredao_contract.py
web3_wizzard_lib/core/contract/coredao_from_contract.py
web3_wizzard_lib/core/contract/dmail_send_mail.py
web3_wizzard_lib/core/contract/empty_nft.py
web3_wizzard_lib/core/contract/era_name.py
web3_wizzard_lib/core/contract/eralendcontract.py
web3_wizzard_lib/core/contract/eth_scroll_bridge_contract.py
web3_wizzard_lib/core/contract/frog_war_contract.py
web3_wizzard_lib/core/contract/gmx_reward_router.py
web3_wizzard_lib/core/contract/horizondex_quoter.py
web3_wizzard_lib/core/contract/horizondex_router.py
web3_wizzard_lib/core/contract/imagine_contract.py
web3_wizzard_lib/core/contract/izumi.py
web3_wizzard_lib/core/contract/kreatorland_contract.py
web3_wizzard_lib/core/contract/l0_claim.py
web3_wizzard_lib/core/contract/l2_telegraph.py
web3_wizzard_lib/core/contract/layerbank_price.py
web3_wizzard_lib/core/contract/layerbank_token.py
web3_wizzard_lib/core/contract/layerbankcontract.py
web3_wizzard_lib/core/contract/linea_day_2_contract.py
web3_wizzard_lib/core/contract/linea_day_3_contract.py
web3_wizzard_lib/core/contract/linea_ens_names_contract.py
web3_wizzard_lib/core/contract/lineaswaprouter.py
web3_wizzard_lib/core/contract/maverick_multicall.py
web3_wizzard_lib/core/contract/mendi_finance_contract.py
web3_wizzard_lib/core/contract/mendi_token.py
web3_wizzard_lib/core/contract/merkly_minter.py
web3_wizzard_lib-1.13.5.dist-info/METADATA
web3_wizzard_lib-1.13.5.dist-info/WHEEL
web3_wizzard_lib-1.13.5.dist-info/top_level.txt
web3_wizzard_lib-1.13.5.dist-info/RECORD
