Metadata-Version: 2.4
Name: web3-wizzard-lib
Version: 1.13.5
Summary: Engine for web3 smart contracts automatization.
Author-email: Indeoo <indeooars@gmail.com>
License: MIT
Project-URL: Homepage, https://github.com/Indeoo/web3-wizzard-lib/
Requires-Python: >=3.7
Requires-Dist: sybil-engine==10.6.3
Requires-Dist: brotli==1.1.0
